__init__.py
calculator.py
calculator_JN-0.0.2.dist-info/LICENSE
calculator_JN-0.0.2.dist-info/METADATA
calculator_JN-0.0.2.dist-info/WHEEL
calculator_JN-0.0.2.dist-info/top_level.txt
calculator_JN-0.0.2.dist-info/RECORD
