Metadata-Version: 2.1
Name: calculator-JN
Version: 0.0.2
Summary: A small calculator package
Author-email: Jiani Song <lovepooh1990@gmail.com>
Project-URL: Homepage, https://github.com/TuringCollegeSubmissions/jisong-DWWP.1.5
Classifier: Programming Language :: Python :: 3
Classifier: License :: OSI Approved :: MIT License
Classifier: Operating System :: OS Independent
Requires-Python: >=3.8
License-File: LICENSE
